LICENSE
MANIFEST.in
README.md
pavement.py
requirements-dev.txt
requirements.txt
setup.cfg
setup.py
tox.ini
docs/Makefile
docs/make.bat
docs/source/README
docs/source/conf.py
docs/source/index.rst
docs/source/_static/.gitkeep
geopdf/__init__.py
geopdf/metadata.py
geopdf.egg-info/PKG-INFO
geopdf.egg-info/SOURCES.txt
geopdf.egg-info/dependency_links.txt
geopdf.egg-info/not-zip-safe
geopdf.egg-info/requires.txt
geopdf.egg-info/top_level.txt
tests/__init__.py
tests/test_main.py