Metadata-Version: 1.1
Name: geopdf
Version: 0.1
Summary: Adds GeoPDF functionality to ReportLab.
Home-page: http://garnertb.io/
Author: Tyler Garner
Author-email: garnertb@gmail.com
License: UNKNOWN
Platform: UNKNOWN
Classifier: Development Status :: 1 - Planning
Classifier: Environment :: Console
Classifier: Intended Audience :: Developers
Classifier: License :: OSI Approved :: MIT License
Classifier: Natural Language :: English
Classifier: Operating System :: OS Independent
Classifier: Programming Language :: Python :: 2.6
Classifier: Programming Language :: Python :: 2.7
Classifier: Topic :: Software Development :: Libraries :: Python Modules
